pytest_results/__init__.py
pytest_results/_exc_group.py
pytest_results/_testinfo.py
pytest_results/exceptions.py
pytest_results/py.typed
pytest_results/_core/__init__.py
pytest_results/_core/regression.py
pytest_results/_core/dump_functions/__init__.py
pytest_results/_core/dump_functions/json.py
pytest_results/_core/storages/__init__.py
pytest_results/_core/storages/abc.py
pytest_results/_core/storages/local.py
pytest_results/contrib/__init__.py
pytest_results/contrib/pytest/__init__.py
pytest_results/contrib/pytest/plugin.py
pytest_results-0.5.0.dist-info/METADATA
pytest_results-0.5.0.dist-info/WHEEL
pytest_results-0.5.0.dist-info/entry_points.txt
pytest_results-0.5.0.dist-info/licenses/LICENSE
pytest_results-0.5.0.dist-info/RECORD
